{
    "name": "Theo's Adventure: Rewritten",
    "version": "0.0.1",
    "description": "",
    "dependencies": {
        "device": "*",
        "Color Fading": "github:jwunderl/pxt-color#v0.2.1",
        "corgio": "*",
        "arcade-tile-util": "github:microsoft/arcade-tile-util#v1.0.1",
        "color-coded-tilemap": "*",
        "arcade-text": "github:microsoft/arcade-text#v1.3.0",
        "pxt-status-bar": "github:jwunderl/pxt-status-bar#v0.4.1"
    },
    "files": [
        "main.ts",
        "README.md",
        "assets.json",
        "tilemap.g.jres",
        "tilemap.g.ts",
        "images.g.jres",
        "images.g.ts",
        "lib.ts",
        "ambow.ts",
        "colors.ts"
    ],
    "testFiles": [
        "test.ts"
    ],
    "targetVersions": {
        "branch": "v1.8.22",
        "tag": "v1.8.22",
        "commits": "https://github.com/microsoft/pxt-arcade/commits/6017af228c87817006b555668c65933bf3cbff4c",
        "target": "1.8.22",
        "pxt": "7.4.26",
        "targetId": "arcade"
    },
    "supportedTargets": [
        "arcade"
    ],
    "preferredEditor": "tsprj",
    "languageRestriction": "javascript-only"
}
